{
  "project_info": {
    "project_number": "533932732600",
    "firebase_url": "https://favo-11728.firebaseio.com",
    "project_id": "favo-11728",
    "storage_bucket": "favo-11728.appspot.com"
  },
  "client": [
    {
      "client_info": {
        "mobilesdk_app_id": "1:533932732600:android:2f0f55765637b541cec44d",
        "android_client_info": {
          "package_name": "ch.epfl.favo"
        }
      },
      "oauth_client": [
        {
          "client_id": "533932732600-o527qjq6r1holvij9a287b1jd2ule3ns.apps.googleusercontent.com",
          "client_type": 1,
          "android_info": {
            "package_name": "ch.epfl.favo",
            "certificate_hash": "fb06ed1b7cf33e0dc5c51c505a3a4cdae8a43530"
          }
        },
        {
          "client_id": "533932732600-mdvm871arhd6mrq8f8fahbth50aj68np.apps.googleusercontent.com",
          "client_type": 1,
          "android_info": {
            "package_name": "ch.epfl.favo",
            "certificate_hash": "79ac47ae638d7640c9ed9125fe4fdfe3758fd149"
          }
        },
        {
          "client_id": "533932732600-b75mtr3mfhuois7n2f3t9alpdfklbj4c.apps.googleusercontent.com",
          "client_type": 3
        }
      ],
      "api_key": [
        {
          "current_key": "AIzaSyBJg0o9dJvCsnD5VbNIAXQTsKYfa_joXBA"
        }
      ],
      "services": {
        "appinvite_service": {
          "other_platform_oauth_client": [
            {
              "client_id": "533932732600-b75mtr3mfhuois7n2f3t9alpdfklbj4c.apps.googleusercontent.com",
              "client_type": 3
            }
          ]
        }
      }
    }
  ],
  "configuration_version": "1"
}